{"type":"FeatureCollection","features":[{"type":"Feature","geometry":{"type":"Point","coordinates":[2.1179138067971985,41.372491452334,0.0]},"properties":{"id":"123166","description":"<img class=\"img-rounded leaflet-popup-image\" src=\"https://www.l-h.cat/utils/obreFitxer.ashx?Fw9EVw48XS5YvLU0awPURBqazAqFOEcLPy0Nb9wqazCR7GqazC2IqazB\"><br><div class=\"btn-group pull-right leaflet-popup-buttons\" role=\"group\"><a class=\"btn btn-default btn-md\" target=\"_blank\" href=\"https://www.l-h.cat/directori/detallequipament.aspx?1kARvPUQtjpCs2HPFYBu9eKw0WEJQbLA2GenIhzICHhqazATBmOblCYziAqazBqazB\" type=\"button\" target=\"_blank\"><i class=\"fa fa-info-circle\"></i></a></div><br></div>","name":"Teatre Joventut"}},{"type":"Feature","geometry":{"type":"Point","coordinates":[2.1005894459629797,41.362755328649243,0.0]},"properties":{"id":"123170","description":"<img class=\"img-rounded leaflet-popup-image\" src=\"https://www.l-h.cat/utils/obreFitxer.ashx?Fw9EVw48XS7V3ARemkPwB742nTg0qjVKaes7yo0cetMqazB\"><br><div class=\"btn-group pull-right leaflet-popup-buttons\" role=\"group\"><a class=\"btn btn-default btn-md\" target=\"_blank\" href=\"https://www.l-h.cat/directori/detallequipament.aspx?16osQjoXPoaxyXbWxYRvuCJjwU3GqazAXQy2G7QYslbLFyqazCXaZYuoGNg7AqazBqazB\" type=\"button\" target=\"_blank\"><i class=\"fa fa-info-circle\"></i></a></div><br></div>","name":"Auditori Barradas"}},{"type":"Feature","geometry":{"type":"Point","coordinates":[2.1233930962866441,41.37051562000277,0.0]},"properties":{"id":"123172","description":"<a href=\"https://www.l-h.cat/directori/detallequipament.aspx?16osQjoXPoaxbnReEuU5b0Apd9kjrUcMGx1f3tAlTPuxHb63lqfH5UgqazBqazB\">[+] Info</a><br /><div class=\"btn-group pull-right leaflet-popup-buttons\" role=\"group\"><a class=\"btn btn-default btn-md\" target=\"_blank\" href=\"https://www.l-h.cat/directori/detallequipament.aspx?16osQjoXPoaxbnReEuU5b0Apd9kjrUcMGx1f3tAlTPuxHb63lqfH5UgqazBqazB\" type=\"button\" target=\"_blank\"><i class=\"fa fa-info-circle\"></i></a></div><br></div>","name":"Auditori La Torrassa"}}],"crs":{"type":"name","properties":{"name":"urn:ogc:def:crs:EPSG::4326"}}}